sampledbapi/__init__.py
sampledbapi/actions.py
sampledbapi/actiontypes.py
sampledbapi/comm.py
sampledbapi/instruments.py
sampledbapi/locations.py
sampledbapi/locationtypes.py
sampledbapi/object_log.py
sampledbapi/objects.py
sampledbapi/users.py
sampledbapi/utils.py
sampledbapi-0.6.6.dist-info/licenses/LICENSE
sampledbapi-0.6.6.dist-info/METADATA
sampledbapi-0.6.6.dist-info/WHEEL
sampledbapi-0.6.6.dist-info/top_level.txt
sampledbapi-0.6.6.dist-info/RECORD
